repovisor/__about__.py
repovisor/__init__.py
repovisor/__main__.py
repovisor/repostate.py
repovisor/repovisor.py
repovisor-0.0.8.dist-info/LICENSE.md
repovisor-0.0.8.dist-info/METADATA
repovisor-0.0.8.dist-info/WHEEL
repovisor-0.0.8.dist-info/entry_points.txt
repovisor-0.0.8.dist-info/top_level.txt
repovisor-0.0.8.dist-info/RECORD
