Metadata-Version: 2.1
Name: repovisor
Version: 0.0.8
Summary: A tool for managing many repositories and creating daily reports
Home-page: https://github.com/gjcooper/repovisor
Author: Gavin Cooper
Author-email: gjcooper@gmail.com
License: BSD
Keywords: git,repository,manager
Platform: UNKNOWN
Classifier: Development Status :: 3 - Alpha
Classifier: Intended Audience :: Developers
Classifier: Programming Language :: Python :: 3
Requires-Dist: click (==7.0)
Requires-Dist: colorama (==0.4.1)
Requires-Dist: gitdb2 (==2.0.5)
Requires-Dist: gitpython (==2.1.11)
Requires-Dist: smmap2 (==2.0.5)
